Mishmash.py
MishmashConfigReader.py
MishmashExceptions.py
MishmashFunction.py
MishmashLiteral.py
MishmashLogger.py
MishmashOp.py
MishmashSet.py
__init__.py
utils.py
mishmash_io_client.egg-info/PKG-INFO
mishmash_io_client.egg-info/SOURCES.txt
mishmash_io_client.egg-info/dependency_links.txt
mishmash_io_client.egg-info/requires.txt
mishmash_io_client.egg-info/top_level.txt
net/MishmashGrpcClient.py
net/MishmashGrpcConfig.py
net/MishmashMessageParser.py
net/MishmashMutation.py
net/MishmashStream.py
net/__init__.py
mishmash_io_client-0.0.10.dist-info/LICENSE
mishmash_io_client-0.0.10.dist-info/METADATA
mishmash_io_client-0.0.10.dist-info/WHEEL
mishmash_io_client-0.0.10.dist-info/top_level.txt
mishmash_io_client-0.0.10.dist-info/RECORD
