Metadata-Version: 2.1
Name: mishmash-io-client
Version: 0.0.10
Summary: mishmash io client library
Home-page: https://mishmash.io
Author: mishmash.io
Author-email: info@mishmash.io
License: Apache License v2.0
Project-URL: Bug Tracker, https://github.com/mishmash-io/mishmash-io-client-python/issues
Project-URL: Documentation, https://mishmash.io
Project-URL: Source Code, https://github.com/mishmash-io/mishmash-io-client-python/
Keywords: database,artificial intelligence,development
Platform: UNKNOWN
Classifier: Intended Audience :: Developers
Classifier: License :: OSI Approved :: Apache Software License
Classifier: Programming Language :: Python
Classifier: Programming Language :: Python :: 3 :: Only
Classifier: Programming Language :: Python :: 3.6
Classifier: Programming Language :: Python :: 3.7
Classifier: Programming Language :: Python :: 3.8
Classifier: Development Status :: 3 - Alpha
Classifier: Topic :: Database
Classifier: Topic :: Utilities
Classifier: Topic :: Scientific/Engineering :: Artificial Intelligence
Classifier: Topic :: Scientific/Engineering :: Information Analysis
Classifier: Topic :: Scientific/Engineering :: Interface Engine/Protocol Translator
Classifier: Topic :: Scientific/Engineering :: Mathematics
Classifier: Topic :: Software Development
Classifier: Topic :: Software Development :: Libraries
Requires-Python: >=3.6, <4
License-File: LICENSE
Requires-Dist: mishmash-io-rpc (>=0.0.5)
Requires-Dist: async-timeout
Provides-Extra: aws
Requires-Dist: mishmash-io-auth-aws (>=0.0.2) ; extra == 'aws'
Provides-Extra: azure
Requires-Dist: mishmash-io-auth-azure (>=0.0.2) ; extra == 'azure'
Provides-Extra: dev
Requires-Dist: pytest ; extra == 'dev'
Provides-Extra: google
Requires-Dist: mishmash-io-auth-google (>=0.0.2) ; extra == 'google'
Provides-Extra: jwt
Requires-Dist: mishmash-io-auth-jwt (>=0.0.2) ; extra == 'jwt'
